etl_toolbox/__init__.py
etl_toolbox/cleaning_functions.py
etl_toolbox/dataframe_functions.py
etl_toolbox/file_functions.py
etl_toolbox/mapping_functions.py
etl_toolbox-0.0.3.dist-info/LICENSE
etl_toolbox-0.0.3.dist-info/METADATA
etl_toolbox-0.0.3.dist-info/WHEEL
etl_toolbox-0.0.3.dist-info/top_level.txt
etl_toolbox-0.0.3.dist-info/RECORD
