Metadata-Version: 2.1
Name: etl-toolbox
Version: 0.0.3
Summary: Useful ETL functions for Python
Home-page: https://etl-toolbox.readthedocs.io
Author: Brooklyn Rose Ludlow
License: Apache-2.0
Project-URL: Source Code, https://github.com/brookcub/etl-toolbox
Project-URL: Bug Reports, https://github.com/brookcub/etl-toolbox/issues
Project-URL: Documentation, https://etl-toolbox.readthedocs.io
Keywords: etl pandas data cleaning
Platform: any
Classifier: Programming Language :: Python
Classifier: Programming Language :: Python :: 3
Classifier: Programming Language :: Python :: 3.5
Classifier: Programming Language :: Python :: 3.6
Classifier: Programming Language :: Python :: 3.7
Classifier: Programming Language :: Python :: 3.8
Classifier: Development Status :: 4 - Beta
Classifier: Natural Language :: English
Classifier: Intended Audience :: Developers
Classifier: License :: OSI Approved :: Apache Software License
Classifier: Operating System :: OS Independent
Classifier: Topic :: Software Development :: Libraries :: Python Modules
Requires-Python: >=3.5
Requires-Dist: numpy (>=1.18.0)
Requires-Dist: pandas (>=0.25.0)
Provides-Extra: testing
Requires-Dist: pytest ; extra == 'testing'
